salt_forgejo/__init__.py
salt_forgejo/modules/__init__.py
salt_forgejo/modules/forgejo.py
salt_forgejo/modules/keygen.py
salt_forgejo/states/__init__.py
salt_forgejo/states/forgejo.py
salt_forgejo/states/keygen.py
salt_forgejo-0.1.0.dist-info/licenses/LICENSE
salt_forgejo-0.1.0.dist-info/WHEEL
salt_forgejo-0.1.0.dist-info/entry_points.txt
salt_forgejo-0.1.0.dist-info/METADATA
salt_forgejo-0.1.0.dist-info/RECORD
