Metadata-Version: 2.4
Name: salt-forgejo
Version: 0.1.0
Summary: Manage Forgejo repositories with Salt
Keywords: forgejo,salt
License-Expression: MIT
License-File: LICENSE
Classifier: Development Status :: 3 - Alpha
Classifier: Intended Audience :: System Administrators
Classifier: Programming Language :: Python :: 3
Requires-Dist: salt>=3006
Project-URL: source, https://codeberg.org/kfdm/salt-forgejo
